elevenlabs_mcp/__init__.py
elevenlabs_mcp/__main__.py
elevenlabs_mcp/convai.py
elevenlabs_mcp/model.py
elevenlabs_mcp/server.py
elevenlabs_mcp/utils.py
mseep_elevenlabs_mcp-0.4.1.dist-info/licenses/LICENSE
mseep_elevenlabs_mcp-0.4.1.dist-info/METADATA
mseep_elevenlabs_mcp-0.4.1.dist-info/WHEEL
mseep_elevenlabs_mcp-0.4.1.dist-info/top_level.txt
mseep_elevenlabs_mcp-0.4.1.dist-info/RECORD
