Metadata-Version: 2.4
Name: mseep-elevenlabs-mcp
Version: 0.4.1
Summary: ElevenLabs MCP Server
Home-page: 
Author: mseep
Author-email: support@skydeck.ai
Maintainer: mseep
Maintainer-email: support@skydeck.ai
Keywords: mseep,elevenlabs,mcp,text-to-speech,speech-to-text,voice-cloning
Classifier: Programming Language :: Python :: 3
Classifier: License :: OSI Approved :: MIT License
Classifier: Operating System :: OS Independent
Requires-Python: >=3.6
License-File: LICENSE
Requires-Dist: mcp[cli]>=1.6.0
Requires-Dist: fastapi==0.109.2
Requires-Dist: uvicorn==0.27.1
Requires-Dist: python-dotenv==1.0.1
Requires-Dist: pydantic>=2.6.1
Requires-Dist: httpx==0.28.1
Requires-Dist: elevenlabs>=2.1.0
Requires-Dist: fuzzywuzzy==0.18.0
Requires-Dist: python-Levenshtein>=0.25.0
Requires-Dist: sounddevice==0.5.1
Requires-Dist: soundfile==0.13.1
Dynamic: author
Dynamic: author-email
Dynamic: classifier
Dynamic: description
Dynamic: description-content-type
Dynamic: keywords
Dynamic: license-file
Dynamic: maintainer
Dynamic: maintainer-email
Dynamic: requires-dist
Dynamic: requires-python
Dynamic: summary
